daily_med/__init__.py
daily_med/daily_med.py
daily_med/exceptions.py
daily_med/hl7.py
daily_med/request_paginator.py
daily_med/models/__init__.py
daily_med/models/spl.py
daily_med/models/spl_document.py
daily_med/tests/__init__.py
daily_med/tests/test_daily_med.py
daily_med/tests/test_request_paginator.py
daily_med/tests/test_spl_document.py
python_daily_med-0.1.0b76.dist-info/DESCRIPTION.rst
python_daily_med-0.1.0b76.dist-info/METADATA
python_daily_med-0.1.0b76.dist-info/RECORD
python_daily_med-0.1.0b76.dist-info/WHEEL
python_daily_med-0.1.0b76.dist-info/metadata.json
python_daily_med-0.1.0b76.dist-info/top_level.txt
