Metadata-Version: 2.0
Name: python-daily-med
Version: 0.1.0b76
Summary: Interact with US NLM Daily Med API using Python.
Home-page: https://laslabs.github.io/python-daily-med
Author: LasLabs Inc.
Author-email: support@laslabs.com
License: MIT
Download-URL: https://github.com/LasLabs/python-daily-med
Platform: UNKNOWN
Classifier: Development Status :: 4 - Beta
Classifier: Environment :: Console
Classifier: Intended Audience :: Developers
Classifier: License :: OSI Approved :: MIT License
Classifier: Programming Language :: Python
Classifier: Topic :: Software Development :: Libraries :: Python Modules
Requires-Dist: lxml
Requires-Dist: properties
Requires-Dist: requests
